py_tzone/__init__.py
py_tzone/__main__.py
py_tzone/tz_info.py
py_tzone-1.6.1.dist-info/LICENSE
py_tzone-1.6.1.dist-info/METADATA
py_tzone-1.6.1.dist-info/WHEEL
py_tzone-1.6.1.dist-info/top_level.txt
py_tzone-1.6.1.dist-info/RECORD
