Metadata-Version: 2.1
Name: py-tzone
Version: 1.6.1
Summary: Python Package to get all the information about a Time Zone
Home-page: https://github.com/prkhrv/py_tzone
Author: prkhrv
Author-email: contact.prkhrv@gmail.com
License: MIT
Platform: UNKNOWN
Classifier: License :: OSI Approved :: MIT License
Classifier: Programming Language :: Python :: 3
Classifier: Programming Language :: Python :: 3.7
